{"dave": {"todo": [], "inProgress": [], "done": [], "taskIdCounter": 0, "timer": {"timeLeft": 1500, "isRunning": false, "elapsedTime": 0, "lastUpdate": null}, "currentTask": null}, "bob": {"todo": [{"id": "task-0", "text": "some", "details": ""}, {"id": "task-1", "text": "tasks", "details": ""}, {"id": "task-3", "text": "for", "details": ""}, {"id": "task-4", "text": "you", "details": ""}], "inProgress": [{"id": "task-2", "text": "are good", "details": "some task details"}], "done": [], "taskIdCounter": 5, "timer": {"timeLeft": 1500, "isRunning": false, "elapsedTime": 0, "lastUpdate": null}, "currentTask": {"id": "task-2", "text": "are good"}}, "Default": {"todo": [], "inProgress": [], "done": [], "taskIdCounter": 0, "timer": {"timeLeft": 1500, "isRunning": false, "elapsedTime": 0, "lastUpdate": null}, "currentTask": null}, "default": {"todo": [], "inProgress": [], "done": [], "taskIdCounter": 0, "timer": {"timeLeft": 1500, "isRunning": false, "elapsedTime": 0, "lastUpdate": null}, "currentTask": null}}